MANIFEST.in
README.rst
setup.py
pypbf/__init__.py
pypbf/pypbf.py
pypbf.egg-info/PKG-INFO
pypbf.egg-info/SOURCES.txt
pypbf.egg-info/dependency_links.txt
pypbf.egg-info/requires.txt
pypbf.egg-info/top_level.txt
pypbf.egg-info/zip-safe